screen_cls/__init__.py
screen_cls/main.py
screen_cls-1.0.7.dist-info/LICENSE
screen_cls-1.0.7.dist-info/METADATA
screen_cls-1.0.7.dist-info/WHEEL
screen_cls-1.0.7.dist-info/top_level.txt
screen_cls-1.0.7.dist-info/RECORD
